docwarrior/__init__.py
docwarrior/cli.py
docwarrior/docwarrior.py
docwarrior-0.1.0.dist-info/AUTHORS.rst
docwarrior-0.1.0.dist-info/LICENSE
docwarrior-0.1.0.dist-info/METADATA
docwarrior-0.1.0.dist-info/WHEEL
docwarrior-0.1.0.dist-info/entry_points.txt
docwarrior-0.1.0.dist-info/top_level.txt
docwarrior-0.1.0.dist-info/RECORD
