Metadata-Version: 2.1
Name: docwarrior
Version: 0.1.0
Summary: Doc management
Home-page: https://github.com/volodymyrss/docwarrior
Author: Volodymyr Savchenko
Author-email: contact@volodymyrsavchenko.com
License: MIT license
Keywords: docwarrior
Platform: UNKNOWN
Classifier: Development Status :: 2 - Pre-Alpha
Classifier: Intended Audience :: Developers
Classifier: License :: OSI Approved :: MIT License
Classifier: Natural Language :: English
Classifier: Programming Language :: Python :: 3
Classifier: Programming Language :: Python :: 3.5
Classifier: Programming Language :: Python :: 3.6
Classifier: Programming Language :: Python :: 3.7
Classifier: Programming Language :: Python :: 3.8
Requires-Python: >=3.5
Requires-Dist: Click (>=7.0)
